{
  "authors": [
    "webtretho.com"
  ],
  "date_download": "2026-04-08 21:37:39",
  "date_modify": null,
  "date_publish": "2020-09-03T03:15:23.000Z",
  "description": "Tác giả: KylieNgười ta hay nói: con gái là tình nhân kiếp trước của bố. Có đáng tin không?Tôi thì chẳng có chút lòng tin vào cái nhận định đó,...",
  "filename": "bai_bao_288_con_gái_là_tình_nhân_kiếp_trước_của_bố.json",
  "image_url": "https://www.webtretho.vn/static/img/logo-b.png?ver=2",
  "language": "vi",
  "localpath": null,
  "maintext": "",
  "source_domain": "www.webtretho.com",
  "title": "Con Gái Là Tình Nhân Kiếp Trước Của Bố",
  "title_page": null,
  "title_rss": null,
  "url": "https://www.webtretho.com/f/sach-truyen-tho/con-gai-la-tinh-nhan-kiep-truoc-cua-bo"
}