{
  "authors": [
    "VCCorp.vn",
    "Thái Hiếu"
  ],
  "date_download": "2026-04-08 23:10:39",
  "date_modify": null,
  "date_publish": "2021-10-23T13:53:00",
  "description": "Tính chung 9 tháng đầu năm 2021 PVIRe lãi sau thuế 91 tỷ đồng, hoản thành 67% chỉ tiêu lợi nhuận được giao cho cả năm.",
  "filename": "bai_bao_474_tái_bảo_hiểm_pvi__pvire__báo_lãi_sau_thuế_quý_3_gi.json",
  "image_url": "https://cafefcdn.com/thumb_w/1200/203337114487263232/2021/10/22/photo1634877145759-16348771458981871601827.png",
  "language": "vi",
  "localpath": null,
  "maintext": "Tổng CTCP Tái bảo hiểm PVI (PVIRe – mã chứng khoán PRE) công bố báo cáo tài chính quý 3/2021 với doanh thu phí bảo hiểm thuần kinh doanh bảo hiểm đạt 257 tỷ đồng, tăng 30,2% so với cùng kỳ. Trừ các chi phí phát sinh, PVIRe lãi gộp 15,8 tỷ đồng từ hoạt động kinh doanh bảo hiểm (giảm 7,9 tỷ đồng so với cùng kỳ chủ yếu do chi phí chi hoa hồng bảo hiểm tăng).\n\nTrong quý công ty ghi nhận doanh thu tài chính đạt hơn 28, giảm 1 tỷ đồng so với cùng kỳ. Doanh thu tài chính của công ty phần lớn từ thu lãi tiền gửi, lãi chênh lệch tỷ giá. Chi phí tài chính xấp xỉ 4 tỷ đồng. Kết quả, quý 3 PVIRe lãi sau thuế 26,2 tỷ đồng, giảm 20% so với cùng kỳ.\n\nLũy kế 9 tháng đầu năm 2021 doanh thu thuần từ hoạt động kinh doanh bảo hiểm của PVIRe đạt 728 tỷ đồng, tăng 17,1% so với cùng kỳ. Lợi nhuận sau thuế giảm 14,8% xuống còn gần 91 tỷ đồng và mới hoàn thành 67% kế hoạch lợi nhuận cả năm. EPS đạt 1.147 đồng.",
  "source_domain": "cafef.vn",
  "title": "Tái bảo hiểm PVI (PVIRe) báo lãi sau thuế quý 3 giảm 20% so với cùng kỳ 2020",
  "title_page": null,
  "title_rss": null,
  "url": "http://cafef.vn/tai-bao-hiem-pvi-pvire-bao-lai-sau-thue-quy-3-giam-20-so-voi-cung-ky-2020-20211022113450803.chn"
}