{
  "authors": [
    "thanhnien.vn",
    "Hoàng Kim-  hoangkim62@gmail.com"
  ],
  "date_download": "2026-04-08 23:24:46",
  "date_modify": null,
  "date_publish": "2021-09-29T06:32:00+07:00",
  "description": "Có lẽ hầu hết soạn giả cải lương đều là những cây bút nam giới với tên tuổi và số lượng hùng hậu. Tuy nhiên, phụ nữ cũng đã góp mặt vào làng cải lương với những tên tuổi đáng nể dù hiếm hoi.",
  "filename": "bai_bao_621_những_nữ_soạn_giả_cải_lương_hiếm_hoi__nsnd_bảy_nam.json",
  "image_url": "https://images2.thanhnien.vn/zoom/1200_630/Uploaded/minhnguyet/2021_09_29/bay-nam1_DQHF.jpg",
  "language": "vi",
  "localpath": null,
  "maintext": "NSND Bảy Nam và NSND Kim Cương trong vở Lá sầu riêng",
  "source_domain": "thanhnien.vn",
  "title": "Những nữ soạn giả cải lương hiếm hoi: NSND Bảy Nam, soạn giả đầu tiên của cải lương",
  "title_page": null,
  "title_rss": null,
  "url": "https://thanhnien.vn/van-hoa/nsnd-bay-nam-soan-gia-dau-tien-cua-cai-luong-1455992.html"
}