{
  "authors": [
    "Yêu Thể Thao"
  ],
  "date_download": "2026-04-08 23:17:44",
  "date_modify": null,
  "date_publish": "2021-10-05T05:28:01+07:00",
  "description": "Tin tức bóng đá hôm nay - bongda.com.vn",
  "filename": "bai_bao_547_mourinho_vượt_allegri__thiết_lập_kỷ_lục_tại_serie_.json",
  "image_url": "https://media.bongda.com.vn/files/news/2021/10/04/mourinho-vuot-allegri-thiet-lap-ky-luc-tai-serie-a-145801.jpg",
  "language": "vi",
  "localpath": null,
  "maintext": "BongDa.com.vnChiến thắng mới đây nhất của AS Roma giúp Jose Mourinho thiết lập kỷ lục mới tại Serie A.\n\nAS Romavừa có chiến thắng nhẹ nhàng 2-0 trước Empoli ở vòng 7 Serie A. Lorenzo Pellegrini và Henrikh Mkhitaryan là bộ đôi lập công cho Roma. Với 3 điểm trước Empoli, đội bóng của Jose Mourinho đã leo lên top 4. Khởi đầu của Mourinho tại CLB thủ đô vẫn vô cùng ấn tượng.\n\nChiến thắng ấy càng thêm phần ý nghĩa khi Mourinho thiết lập kỷ lục mới tại Serie A. Chiến lược gia người Bồ Đào Nha đã vượt qua Max Allegri để trở thành HLV chạm đến số trận bất bại liên tiếp trên sân nhà dài nhất ở Serie A với con số 42 trận. Trong khi đó, Allegri chỉ mới sở hữu chuỗi 41 trận bất bại tại sân nhà. Được biết, thành tích của “Người đặc biệt” bắt đầu ở Inter Milan vào năm 2008.\n\nMourinholuôn được biết đến là HLV sở hữu thành tích tốt ở sân nhà. Tại Ngoại hạng Anh cùng Chelsea trong giai đoạn 2004-2007, ông từng thiết lập kỷ lục tương tự. Từng có thời điểmnhà cầm quân người Bồ Đào Nhađược sử sách Guiness vinh danh vì thành tích bất bại trên sân nhà trong 9 năm qua các CLB như Porto, Chelsea, Inter hay Real.\n\nMourinho có thể đang bị đánh giá lạc hậu so với guồng quay của thế giới bóng đá. Song, điều đó không thể phủ nhận những chiến tích mà ông có trong môn thể thao vua từ quá khứ đến hiện tại.\n\nVideo Mourinho trả lời phỏng vấn:",
  "source_domain": "www.bongda.com.vn",
  "title": "Mourinho vượt Allegri, thiết lập kỷ lục tại Serie A",
  "title_page": null,
  "title_rss": null,
  "url": "https://www.bongda.com.vn/mourinho-vuot-allegri-thiet-lap-ky-luc-tai-serie-a-d615643.html"
}